Workbook

Sheet Balance Sheet

Sheet Income Statement

Sheet Cash Flow Statement

Sheet Data
A2: MARKET DATA (thousands) | E2: CALCULATED DATA
A3: US 10-years T.Bond (Risk-free rate) | B3: 0.04181 | C3: Source: Investing (24/10/2022) | E3: WACC | F3: =WACC!E12 -> 0.090598563
A4: ERP (USA) | B4: 0.0424 | C4: Source: Damodaran Website | E4: Beta Levered | F4: =Beta!C10 -> 1.0010745
A5: Unlevered Business Beta (Industry: Entertainment) | B5: 0.91 | C5: Source: Damodaran Website | E5: KE | F5: ='Cost of Equity'!D13 -> 0.098042996
A6: Shares | B6: 442895 | C6: Annual Report (2021) | E6: D/E | F6: =B13/B8 -> 0.13709839
A7: Price per share | B7: 241.98 | C7: 17/10/22 Source:Yahoo Finance | E7: Market Value of Debt (thousands) | F7: ='Cost of Debt'!AE13 -> 14670558
A8: Market capitalization (Equity) | B8: =B7*B6 -> 1.0717173e+08 | E8: Interest C.R. | F8: =B15/B17 -> 7.8819276
A9: Marginal tax rate | B9: 0.27 | C9: Source: Damodaran Website | E9: Pre-tax KD | F9: =Data!B3+'Cost of Debt'!AB9 -> 0.04961
E10: Aft. Tax KD | F10: ='Cost of Debt'!AH3 -> 0.0362153
E11: Def. Spread | F11: 0.0078
A12: FINANCIAL DATA (thousands)
A13: Long-term debt (2021, Balance Sheet) | B13: 14693072
A14: Current EBIT | B14: 6194509 | E14: Source: Netflix Investors, 2022 Quarterly Earnings
A15: Current EBIT TTM | B15: =SUM(E18:H18) -> 5714697 | E15: Three Months Ended (thousands)
A16: Current Interest Expense | B16: 765620 | E16: December 31, | F16: March 31, | G16: June 30, | H16: September 30,
A17: Current Interest Expense TTM | B17: =SUM(E19:H19) -> 725038 | E17: 2021 | F17: 2022 | G17: 2022 | H17: 2022
D18: EBIT | E18: 631770 | F18: 1971626 | G18: 1578283 | H18: 1533018
D19: Interest Expense | E19: 189429 | F19: 187579 | G19: 175455 | H19: 172575

Sheet CRP
B3: Region | C3: CRP for macro-regions (Source: Damodaran website)
B4: USA & Canada | C4: 0
B5: Western Europe | C5: 0.0083
B6: Eastern Europe & Russia | C6: 0.0211
B7: Middle East | C7: 0.016
B8: Africa | C8: 0.0525
B9: Latina America | C9: 0.0379
B10: Asia | C10: 0.0104
B11: Australia & New Zeland | C11: 0
B15: Country | C15: Sales (Annual Report 2021) | D15: Sales % | E15: CRP | F15: WA CRP
B16: USA & Canada | C16: 12972.1 | D16: =C16/$C$20 -> 0.43950134 | E16: =C4 -> 0 | F16: =D16*E16 -> 0
B17: Europe, Middle East and Africa | C17: 9699.819 | D17: =C17/$C$20 -> 0.3286348 | E17: =AVERAGE(C5:C8) -> 0.024475 | F17: =D17*E17 -> 0.0080433366
B18: Latin America | C18: 3576.976 | D18: =C18/$C$20 -> 0.12118976 | E18: =C9 -> 0.0379 | F18: =D18*E18 -> 0.0045930921
B19: Asia Pacific | C19: 3266.601 | D19: =C19/$C$20 -> 0.1106741 | E19: =C10 -> 0.0104 | F19: =D19*E19 -> 0.0011510107
B20: Total | C20: =SUM(C16:C19) -> 29515.496 | F20: =SUM(F16:F19) -> 0.013787439

Sheet Beta
B10: Beta levered = | C10: =Data!B5*(1+(Data!F6)*(1-Data!B9)) -> 1.0010745

Sheet Cost of Equity
C13: Cost of equity = | D13: =Data!B3 + Data!F4*Data!B4 + CRP!F20 -> 0.098042996

Sheet Cost of Debt
P3: Debt structure in 31/12/2021 | AD3: Pre-tax Cost of Debt = | AE3: =Data!B3+AB9 -> 0.04961 | AG3: After-tax Cost of Debt = | AH3: =AE3*(1-Data!B9) -> 0.0362153
P4: Maturity | Q4: Senior debt (in millions) | R4: Years | S4: %Debt | T4: W.A. Maturity | W4: Interest coverage ratio | Y4: Corporate Default Spread
P5: 2022 | Q5: 700 | R5: 1 | S5: =Q5/$Q$13 -> 0.045205037 | T5: =R5*S5 -> 0.045205037 | W5: =Data!B15/Data!B17 -> 7.8819276 | Y5: For developed market firms with market cap > $5 billion | AD5: Year 1 | AE5: =Data!$B$17*(1+$AE$3)^-1 -> 690768.95
P6: 2022-24 | Q6: 400 | R6: 3 | S6: =Q6/$Q$13 -> 0.02583145 | T6: =R6*S6 -> 0.077494349 | Y6: If interest coverage ratio is | AD6: Year 2 | AE6: =Data!$B$17*(1+$AE$3)^-2 -> 658119.64
P7: 2022-25 | Q7: =800+535+500 -> 1835 | R7: 4 | S7: =Q7/$Q$13 -> 0.11850178 | T7: =R7*S7 -> 0.4740071 | Y7: > | Z7: ≤ to | AA7: Rating is | AB7: Spread is | AD7: Year 3 | AE7: =Data!$B$17*(1+$AE$3)^-3 -> 627013.5
P8: 2022-26 | Q8: 1000 | R8: 5 | S8: =Q8/$Q$13 -> 0.064578624 | T8: =R8*S8 -> 0.32289312 | Y8: 8.50 | Z8: 100000 | AA8: Aaa/AAA | AB8: 0.0063 | AD8: Year 4 | AE8: =Data!$B$17*(1+$AE$3)^-4 -> 597377.59
P9: 2022-27 | Q9: 1480 | R9: 6 | S9: =Q9/$Q$13 -> 0.095576364 | T9: =R9*S9 -> 0.57345819 | Y9: 6.5 | Z9: 8499999 | AA9: Aa2/AA | AB9: 0.0078 | AD9: Year 5 | AE9: =Data!$B$17*(1+$AE$3)^-5 -> 569142.44
P10: 2022-28 | Q10: =1600+1900 -> 3500 | R10: 7 | S10: =Q10/$Q$13 -> 0.22602519 | T10: =R10*S10 -> 1.5821763 | Y10: 5.5 | Z10: 6499999 | AA10: A1/A+ | AB10: 0.0098 | AD10: Year 6 | AE10: =Data!$B$17*(1+$AE$3)^-6 -> 542241.82
P11: 2022-29 | Q11: =1252+800+1366+900 -> 4318 | R11: 8 | S11: =Q11/$Q$13 -> 0.2788505 | T11: =R11*S11 -> 2.230804 | Y11: 4.25 | Z11: 5499999 | AA11: A2/A | AB11: 0.0108 | AD11: Year 7 | AE11: =Data!$B$17*(1+$AE$3)^-7 -> 516612.67
P12: 2022-30 | Q12: =1252+1000 -> 2252 | R12: 9 | S12: =Q12/$Q$13 -> 0.14543106 | T12: =R12*S12 -> 1.3088796 | Y12: 3 | Z12: 4249999 | AA12: A3/A- | AB12: 1.22 | AD12: Year 7 | AE12: =Data!B13*(1+AE3)^-7 -> 10469282
Q13: =SUM(Q5:Q12) -> 15485 | T13: =SUM(T5:T12) -> 6.6149177 | Y13: 2.5 | Z13: 2999999 | AA13: Baa2/BBB | AB13: 0.0156 | AE13: =SUM(AE5:AE12) -> 14670558 | AF13: Market value of Debt
Y14: 2.25 | Z14: 2249999 | AA14: Ba1/BB+ | AB14: 0.02
Y15: 2 | Z15: 22499999 | AA15: Ba2/BB | AB15: 0.024
Y16: 1.75 | Z16: 1999999 | AA16: B1/B+ | AB16: 3.51
Y17: 1.5 | Z17: 1749999 | AA17: B2/B | AB17: 0.0421
Y18: 1.25 | Z18: 1499999 | AA18: B3/B- | AB18: 0.0515
Y19: 0.8 | Z19: 1249999 | AA19: Caa/CCC | AB19: 0.082
Y20: 0.65 | Z20: 0.799999 | AA20: Ca2/CC | AB20: 0.0864
Y21: 0.2 | Z21: 0.649999 | AA21: C2/C | AB21: 0.1134
Y22: -100000 | Z22: 0.199999 | AA22: D2/D | AB22: 0.1512

Sheet WACC
D12: WACC = | E12: =('Cost of Equity'!D13*WACC!E17)+(Data!F10*WACC!E18) -> 0.090598563
D17: E/(E+D) | E17: =Data!B8/(Data!B8+'Cost of Debt'!AE13) -> 0.87959387
D18: D/(E+D) | E18: ='Cost of Debt'!AE13/('Cost of Debt'!AE13+Data!B8) -> 0.12040613

Sheet R&D
B3: Years | C3: R&D Expense (in thousands) | D3: Accumulated Depreciation 31/12/2021 | F3: Unamortized Portion 31/12/21 | H3: Amortization 31/12/21
B4: 2021 | C4: 2274000 | D4: 0.2 | E4: =C4*D4 -> 454800 | F4: 0.8 | G4: =C4*F4 -> 1819200 | H4: 0.2 | I4: =C4*H4 -> 454800
B5: 2020 | C5: 1830000 | D5: 0.4 | E5: =C5*D5 -> 732000 | F5: 0.6 | G5: =C5*F5 -> 1098000 | H5: 0.2 | I5: =C5*H5 -> 366000
B6: 2019 | C6: 1545000 | D6: 0.6 | E6: =C6*D6 -> 927000 | F6: 0.4 | G6: =C6*F6 -> 618000 | H6: 0.2 | I6: =C6*H6 -> 309000
B7: 2018 | C7: 1222000 | D7: 0.8 | E7: =C7*D7 -> 977600 | F7: 0.2 | G7: =C7*F7 -> 244400 | H7: 0.2 | I7: =C7*H7 -> 244400
B8: 2017 | C8: 953.7 | D8: 1 | E8: =C8*D8 -> 953.7 | F8: 0 | G8: =C8*F8 -> 0 | H8: 0.2 | I8: =C8*H8 -> 190.74
G9: =SUM(G4:G8) -> 3779600 | I9: =SUM(I4:I8) -> 1374390.7
G10: Value of R&D asset | I10: Amortization of Research asset
C13: All numbers in thousands | F13: All numbers in thousands
B14: Operating Income | C14: =Data!B14 -> 6194509 | E14: ADJ Operating Income | F14: =C14+$C$4-$I$9 -> 7094118.3
B15: Net Income | C15: 5116228 | E15: ADJ Net Income | F15: =C15+$C$4-$I$9 -> 6015837.3
B16: Book Value of Equity | C16: 15849248 | E16: ADJ BV Equity | F16: =C16+$G$9 -> 19628848
B17: Book Value of Capital | C17: =C16+Data!B13 -> 30542320 | E17: ADJ BV Capital | F17: =C17+$G$9 -> 34321920

Sheet CAPEX
F3: Source: Annual report
C4: All numbers in thousands | F4: CAPEX (in thousands)
B5: CAPEX | C5: =F7 -> 524585
B6: D&A | C6: =F11 -> 208412 | F6: 2021 | G6: 2020 | H6: 2019 | I6: 2018 | J6: 2017
B7: Net CAPEX | C7: =C5-C6 -> 316173 | F7: 524585 | G7: 497923 | H7: 253035 | I7: 173946 | J7: 173302
B8: R&D EXP | C8: ='R&D'!C4 -> 2274000 | F8: D&A (in thousands)
B9: Amortization R&D | C9: ='R&D'!I9 -> 1374390.7
B10: Norm. Acquisitions (ave5y) | C10: =AVERAGE(F15:J15) -> 157669.8 | F10: 2021 | G10: 2020 | H10: 2019 | I10: 2018 | J10: 2017
B11: ADJ NET CAPEX | C11: =C7+C8-C9+C10 -> 1373452.1 | F11: 208412 | G11: 115710 | H11: 103579 | I11: 83157 | J11: 71911
F12: ACQUISITIONS (in thousands)
F14: 2021 | G14: 2020 | H14: 2019 | I14: 2018 | J14: 2017
F15: 788349 | G15: 0 | H15: 0 | I15: 0 | J15: 0

Sheet NON CASH NWC
B3: (All numbers in thousands) | C3: 2021 | D3: 2020 | E3: 2019 | F3: 2018 | G3: 2017 | H3: Hist. Average
B4: Δ Inventory | C4: 0 | D4: 0 | E4: 0 | F4: 0 | G4: 0
B5: Δ Receivables | C5: 804320 | D5: 610819 | E5: 454399 | F5: 362712 | G5: 0
B6: Δ Payables | C6: 145115 | D6: -41605 | E6: 96063 | F6: 199198 | G6: 74559
B7: Δ NonCash Net WC | C7: =C4+C5-C6 -> 659205 | D7: =D4+D5-D6 -> 652424 | E7: =E4+E5-E6 -> 358336 | F7: =F4+F5-F6 -> 163514 | G7: =G4+G5-G6 -> -74559
B8: Revenues | C8: 29697844 | D8: 24996056 | E8: 20156447 | F8: 15794341 | G8: 11692713
B9: Δ NC NWC as % of Revenues | C9: =C7/C8 -> 0.022197066 | D9: =D7/D8 -> 0.026101078 | E9: =E7/E8 -> 0.017777736 | F9: =F7/F8 -> 0.010352695 | G9: =G7/G8 -> -0.0063765355 | H9: =AVERAGE(C9:G9) -> 0.014010408
B10: Est. Δ NonCash Net WC Need | C10: =C8*H9 -> 416078.91

Sheet FCFF
C4: Reinvestment Needs (in thousands) | D4: ='NON CASH NWC'!C10+CAPEX!C11 -> 1789531
C5: Reinvestment Rate | D5: =D4/D8 -> 0.3455556
C6: Adj. Op.Income | D6: ='R&D'!F14 -> 7094118.3
C7: Marginal tax rate | D7: =Data!B9 -> 0.27
C8: Adj. After-Tax Op.Income | D8: =D6*(1-D7) -> 5178706.3
C9: FCFF | D9: =D8-D4 -> 3389175.4
D10: or
D11: =D8*(1-D5) -> 3389175.4

Sheet GROWTH
B3: Adj. After-Tax Op.Income | C3: =FCFF!D8 -> 5178706.3 | E3: BV Equity (Balance Sheet) | F3: 15849248 | H3: Sales | I3: ='NON CASH NWC'!C8 -> 29697844
B4: Sales | C4: ='NON CASH NWC'!C8 -> 29697844 | E4: BV Debt | F4: =Data!B13 -> 14693072 | H4: Invested Capital (IC) | I4: =F3+F4-F5 -> 24514516
B5: Return on Sales (ROS) | C5: =C3/C4 -> 0.17437988 | E5: Cash and cash equivalents (Balance Sheet) | F5: 6027804 | H5: Sales to capital ratio | I5: =I3/I4 -> 1.2114391
E6: Value of R&D asset | F6: ='R&D'!G9 -> 3779600
B8: Return on Invested Capital (ROIC) | C8: =C5*I5 -> 0.2112506
E9: Adj. ROIC | F9: =C3/(F3+F4-F5+F6) -> 0.18303121 | H9: Reinvestment Rate | I9: =FCFF!D5 -> 0.3455556
B10: goi | C10: =F9*I9 -> 0.06324746 | E10: Industry ROIC (Entertainment) | F10: 0.1123 | H10: Industry RR | I10: 0.0405
B11: Industry goi | C11: =F10*I10 -> 0.00454815
I12: WACC | J12: =WACC!E12 -> 0.090598563
I13: Risk-free rate | J13: =Data!B3 -> 0.04181
B14: High-growth period
B15: Year | C15: 1 | D15: 2 | E15: 3 | F15: 4 | G15: 5
B16: High-growth rate | C16: =$C$10 -> 0.06324746 | D16: =$C$10 -> 0.06324746 | E16: =$C$10 -> 0.06324746 | F16: =$C$10 -> 0.06324746 | G16: =$C$10 -> 0.06324746
B17: Adj. After-Tax Op.Income | C17: =C3*(1+C16) -> 5506246.4 | D17: =C17*(1+D16) -> 5854502.4 | E17: =D17*(1+E16) -> 6224784.9 | F17: =E17*(1+F16) -> 6618486.7 | G17: =F17*(1+G16) -> 7037089.2
B18: Reinvestment Rate | C18: =$I$9 -> 0.3455556 | D18: =$I$9 -> 0.3455556 | E18: =$I$9 -> 0.3455556 | F18: =$I$9 -> 0.3455556 | G18: =$I$9 -> 0.3455556
B19: FCFF | C19: =C17*(1-C18) -> 3603532.1 | D19: =D17*(1-D18) -> 3831446.3 | E19: =E17*(1-E18) -> 4073775.6 | F19: =F17*(1-F18) -> 4331431.6 | G19: =G17*(1-G18) -> 4605383.6
B20: WACC | C20: =$J$12 -> 0.090598563 | D20: =$J$12 -> 0.090598563 | E20: =$J$12 -> 0.090598563 | F20: =$J$12 -> 0.090598563 | G20: =$J$12 -> 0.090598563
B21: PV FCFF | C21: =C19/(1+C20)^C15 -> 3304178.3 | D21: =D19/(1+D20)^D15 -> 3221312.9 | E21: =E19/(1+E20)^E15 -> 3140525.6 | F21: =F19/(1+F20)^F15 -> 3061764.4 | G21: =G19/(1+G20)^G15 -> 2984978.5
G22: =SUM(C21:G21) -> 15712760
B25: Stable-growth rate | C25: =J13 -> 0.04181 | E25: Value Operating Assets | F25: =C31+G22 -> 68161572
B26: Stable ROIC | C26: =J12 -> 0.090598563 | E26: + Cash | F26: =F5 -> 6027804
B27: Stable RR | C27: =C25/C26 -> 0.46148635 | E27: +/- MV Holdings | F27: 0
B28: Adj. After-Tax Op.Income Y6 | C28: =G17*(1+C25) -> 7331309.9 | E28: - MV Debt | F28: =Data!F7 -> 14670558
B29: FCFF Y6 | C29: =C28*(1-C27) -> 3948010.4 | E29: Value of Equity | F29: =F25+F26+F27-F28 -> 59518818
B30: Terminal Value | C30: =C29/(C26-C25) -> 80920818 | E30: # Shares | F30: =Data!B6 -> 442895
B31: PV Terminal Value | C31: =C30/(1+J12)^5 -> 52448813 | E31: Value per share | F31: =F29/F30 -> 134.38584
E32: Current price (16/12/2022) | F32: 290.71
